arduino_timer_one/__init__.py
arduino_timer_one/Arduino/TimerOne/.git
arduino_timer_one/Arduino/TimerOne/README.md
arduino_timer_one/Arduino/TimerOne/TimerOne.cpp
arduino_timer_one/Arduino/TimerOne/TimerOne.h
arduino_timer_one/Arduino/TimerOne/keywords.txt
arduino_timer_one/Arduino/TimerOne/library.json
arduino_timer_one/Arduino/TimerOne/library.properties
arduino_timer_one/Arduino/TimerOne/config/known_16bit_timers.h
arduino_timer_one/Arduino/TimerOne/examples/FanSpeed/FanSpeed.pde
arduino_timer_one/Arduino/TimerOne/examples/Interrupt/Interrupt.pde
arduino_timer_one/lib/arduino-timer-one.tar.gz
arduino_timer_one-1.1.post1.dist-info/DESCRIPTION.rst
arduino_timer_one-1.1.post1.dist-info/METADATA
arduino_timer_one-1.1.post1.dist-info/RECORD
arduino_timer_one-1.1.post1.dist-info/WHEEL
arduino_timer_one-1.1.post1.dist-info/metadata.json
arduino_timer_one-1.1.post1.dist-info/top_level.txt
