Metadata-Version: 2.0
Name: arduino-timer-one
Version: 1.1.post1
Summary: Python packaging of an Arduino library for configuring the  hardware timer called Timer1 on various Arduino-compatible boards. The original library is available here: https://github.com/PaulStoffregen/TimerOne
Home-page: https://github.com/wheeler-microfluidics/arduino-timer-one
Author: Ryan Fobel
Author-email: ryan@fobel.net
License: CC BY 3.0 US
Keywords: arduino timers
Platform: UNKNOWN
